python_realesrgan_ncnn_vulkan-1.1.data/data/include/glslang/build_info.h
python_realesrgan_ncnn_vulkan-1.1.data/data/include/glslang/Include/BaseTypes.h
python_realesrgan_ncnn_vulkan-1.1.data/data/include/glslang/Include/Common.h
python_realesrgan_ncnn_vulkan-1.1.data/data/include/glslang/Include/ConstantUnion.h
python_realesrgan_ncnn_vulkan-1.1.data/data/include/glslang/Include/InfoSink.h
python_realesrgan_ncnn_vulkan-1.1.data/data/include/glslang/Include/InitializeGlobals.h
python_realesrgan_ncnn_vulkan-1.1.data/data/include/glslang/Include/PoolAlloc.h
python_realesrgan_ncnn_vulkan-1.1.data/data/include/glslang/Include/ResourceLimits.h
python_realesrgan_ncnn_vulkan-1.1.data/data/include/glslang/Include/ShHandle.h
python_realesrgan_ncnn_vulkan-1.1.data/data/include/glslang/Include/SpirvIntrinsics.h
python_realesrgan_ncnn_vulkan-1.1.data/data/include/glslang/Include/Types.h
python_realesrgan_ncnn_vulkan-1.1.data/data/include/glslang/Include/arrays.h
python_realesrgan_ncnn_vulkan-1.1.data/data/include/glslang/Include/glslang_c_interface.h
python_realesrgan_ncnn_vulkan-1.1.data/data/include/glslang/Include/glslang_c_shader_types.h
python_realesrgan_ncnn_vulkan-1.1.data/data/include/glslang/Include/intermediate.h
python_realesrgan_ncnn_vulkan-1.1.data/data/include/glslang/MachineIndependent/Initialize.h
python_realesrgan_ncnn_vulkan-1.1.data/data/include/glslang/MachineIndependent/LiveTraverser.h
python_realesrgan_ncnn_vulkan-1.1.data/data/include/glslang/MachineIndependent/ParseHelper.h
python_realesrgan_ncnn_vulkan-1.1.data/data/include/glslang/MachineIndependent/RemoveTree.h
python_realesrgan_ncnn_vulkan-1.1.data/data/include/glslang/MachineIndependent/Scan.h
python_realesrgan_ncnn_vulkan-1.1.data/data/include/glslang/MachineIndependent/ScanContext.h
python_realesrgan_ncnn_vulkan-1.1.data/data/include/glslang/MachineIndependent/SymbolTable.h
python_realesrgan_ncnn_vulkan-1.1.data/data/include/glslang/MachineIndependent/Versions.h
python_realesrgan_ncnn_vulkan-1.1.dist-info/LICENSE.txt
python_realesrgan_ncnn_vulkan-1.1.dist-info/METADATA
python_realesrgan_ncnn_vulkan-1.1.dist-info/WHEEL
python_realesrgan_ncnn_vulkan-1.1.dist-info/top_level.txt
python_realesrgan_ncnn_vulkan-1.1.dist-info/RECORD
